pathfinder/__init__.py
pathfinder/_pathfinder.cp37-win32.pyd
pathfinder/followers.py
pathfinder/modifiers.py
pathfinder/version.py
robotpy_pathfinder-0.2.6.dist-info/LICENSE
robotpy_pathfinder-0.2.6.dist-info/METADATA
robotpy_pathfinder-0.2.6.dist-info/WHEEL
robotpy_pathfinder-0.2.6.dist-info/top_level.txt
robotpy_pathfinder-0.2.6.dist-info/RECORD
