Metadata-Version: 2.1
Name: robotpy-pathfinder
Version: 0.2.6
Summary: RobotPy bindings for Jaci R's PathFinder library
Home-page: https://github.com/robotpy/robotpy-pathfinder
Author: Dustin Spicuzza
Author-email: dustin@virtualroadside.com
License: MIT
Platform: UNKNOWN
